chat_decode.py
color.py
wanalyzer-0.5.data/scripts/wanalyzer
wanalyzer-0.5.dist-info/METADATA
wanalyzer-0.5.dist-info/WHEEL
wanalyzer-0.5.dist-info/top_level.txt
wanalyzer-0.5.dist-info/RECORD
