Metadata-Version: 2.1
Name: wanalyzer
Version: 0.5
Summary: A WhatsApp Chat Analyzer Script
Home-page: https://github.com/rahuladream/Whatsapp-Chat-Analyzer/
Author: Rahul Singh
Author-email: rahul.singh4800@gmail.com
License: UNKNOWN
Platform: UNKNOWN
Classifier: Programming Language :: Python :: 3
Classifier: License :: OSI Approved :: MIT License
Classifier: Operating System :: OS Independent
Requires-Dist: emoji
Requires-Dist: python-dateutil
